sqlcore/__init__.py
sqlcore/async_connector.py
sqlcore/connector.py
sqlcore-0.1.0.dist-info/LICENSE
sqlcore-0.1.0.dist-info/METADATA
sqlcore-0.1.0.dist-info/WHEEL
sqlcore-0.1.0.dist-info/RECORD
