Metadata-Version: 2.3
Name: sqlcore
Version: 0.1.0
Summary: A simple, lightweight DB connector that allows queries and interactions through raw SQL
License: MIT
Author: Alastair Grant
Author-email: 85125580+aldo-g@users.noreply.github.com
Requires-Python: >=3.10,<4.0
Classifier: License :: OSI Approved :: MIT License
Classifier: Programming Language :: Python :: 3
Classifier: Programming Language :: Python :: 3.10
Classifier: Programming Language :: Python :: 3.11
Classifier: Programming Language :: Python :: 3.12
Classifier: Programming Language :: Python :: 3.13
Requires-Dist: pyodbc (>=5.2.0,<6.0.0)
Requires-Dist: pytest-asyncio (>=0.25.3,<0.26.0)
